FPGA_Test/top.v
// top.v - simple LED counter for FPGA
// Assumptions:
// - The board provides a clock input named `clk` (map your actual clock pin in the .cst file)
// - The LED pins are exposed as an 8-bit bus named `led` (map these signal names to board pins in io_tangnano9k.cst)
// If your .cst uses different signal names (for example LED0..LED7), either rename the
// outputs here or change the pin names in the .cst to match `led[0]`..`led[7]`.

module top (
    input  clk,            // external clock (map this pin in .cst)
    output [5:0] led       // 6 LEDs (led[0] is LSB, led[5] is MSB)
);

    // 6-bit free-running counter. It counts 0..63 and directly drives the 6 LEDs.
    // Note: counting on every FPGA clock edge may be very fast; this matches your
    // request to make the counter 6 bits only. If you want visible slow blinking,
    // either feed a slower clock or add a wider prescaler.

    // Use a wider counter for slower blinking (24 bits => bits 23 downto 0)
    localparam COUNTER_WIDTH = 8;
    reg [COUNTER_WIDTH-1:0] counter = 0;

    always @(posedge clk) begin
        counter <= counter + 1'b1;
    end

    // Directly present the counter on the LED pins
    // Use the top 6 bits of the counter. previous code referenced bit 24 which is out of range
    // for a 24-bit counter (0..23). Use COUNTER_WIDTH-1 downto COUNTER_WIDTH-6 instead.
    assign led[5:0] = counter[COUNTER_WIDTH-1:COUNTER_WIDTH-6]; // upper 6 bits for visible blinking

endmodule

FPGA_Test/top_tb.v
`timescale 1ns/1ps

// test.tb - fixed testbench for top.v
// Simulates the `top` module for a short time and writes a VCD file (test.vcd).

module test;
    // Testbench clock and DUT wires
    reg clk;
    wire [5:0] led;

    // Instantiate the design under test
    top uut (
        .clk(clk),
        .led(led)
    );

    // Clock generation: use 27 MHz clock
    // Period ~= 37 ns (integer ns)
    localparam integer PERIOD_NS = 1000000000 / 27000000; // ns (integer)
    localparam integer HALF = PERIOD_NS / 2;

    initial begin
        clk = 0;
        forever #(HALF) clk = ~clk;
    end

    // Run simulation for a short time
    initial begin
        $display("Starting simulation at %0t ns", $time);
        $dumpfile("test.vcd");
        $dumpvars(0, test);
        $monitor("%0t ns : clk=%b led=%b", $time, clk, led);

        // 10 us = 10_000 ns
        #10000;

        $display("Ending simulation at %0t ns", $time);
        $finish;
    end

endmodule

FPGA_Test/test.vcd
$date
	Thu Nov 27 18:07:37 2025
$end
$version
	Icarus Verilog
$end
$timescale
	1ps
$end
$scope module test $end
$var wire 6 ! led [5:0] $end
$var parameter 32 " HALF $end
$var parameter 32 # PERIOD_NS $end
$var reg 1 $ clk $end
$scope module uut $end
$var wire 1 $ clk $end
$var wire 6 % led [5:0] $end
$var parameter 32 & COUNTER_WIDTH $end
$var reg 8 ' counter [7:0] $end
$upscope $end
$upscope $end
$enddefinitions $end
$comment Show the parameter values. $end
$dumpall
b1000 &
b100101 #
b10010 "
$end
#0
$dumpvars
b0 '
b0 %
0$
b0 !
$end
#18000
b1 '
1$
#36000
0$
#54000
b10 '
1$
#72000
0$
#90000
b11 '
1$
#108000
0$
#126000
b1 !
b1 %
b100 '
1$
#144000
0$
#162000
b101 '
1$
#180000
0$
#198000
b110 '
1$
#216000
0$
#234000
b111 '
1$
#252000
0$
#270000
b10 !
b10 %
b1000 '
1$
#288000
0$
#306000
b1001 '
1$
#324000
0$
#342000
b1010 '
1$
#360000
0$
#378000
b1011 '
1$
#396000
0$
#414000
b11 !
b11 %
b1100 '
1$
#432000
0$
#450000
b1101 '
1$
#468000
0$
#486000
b1110 '
1$
#504000
0$
#522000
b1111 '
1$
#540000
0$
#558000
b100 !
b100 %
b10000 '
1$
#576000
0$
#594000
b10001 '
1$
#612000
0$
#630000
b10010 '
1$
#648000
0$
#666000
b10011 '
1$
#684000
0$
#702000
b101 !
b101 %
b10100 '
1$
#720000
0$
#738000
b10101 '
1$
#756000
0$
#774000
b10110 '
1$
#792000
0$
#810000
b10111 '
1$
#828000
0$
#846000
b110 !
b110 %
b11000 '
1$
#864000
0$
#882000
b11001 '
1$
#900000
0$
#918000
b11010 '
1$
#936000
0$
#954000
b11011 '
1$
#972000
0$
#990000
b111 !
b111 %
b11100 '
1$
#1008000
0$
#1026000
b11101 '
1$
#1044000
0$
#1062000
b11110 '
1$
#1080000
0$
#1098000
b11111 '
1$
#1116000
0$
#1134000
b1000 !
b1000 %
b100000 '
1$
#1152000
0$
#1170000
b100001 '
1$
#1188000
0$
#1206000
b100010 '
1$
#1224000
0$
#1242000
b100011 '
1$
#1260000
0$
#1278000
b1001 !
b1001 %
b100100 '
1$
#1296000
0$
#1314000
b100101 '
1$
#1332000
0$
#1350000
b100110 '
1$
#1368000
0$
#1386000
b100111 '
1$
#1404000
0$
#1422000
b1010 !
b1010 %
b101000 '
1$
#1440000
0$
#1458000
b101001 '
1$
#1476000
0$
#1494000
b101010 '
1$
#1512000
0$
#1530000
b101011 '
1$
#1548000
0$
#1566000
b1011 !
b1011 %
b101100 '
1$
#1584000
0$
#1602000
b101101 '
1$
#1620000
0$
#1638000
b101110 '
1$
#1656000
0$
#1674000
b101111 '
1$
#1692000
0$
#1710000
b1100 !
b1100 %
b110000 '
1$
#1728000
0$
#1746000
b110001 '
1$
#1764000
0$
#1782000
b110010 '
1$
#1800000
0$
#1818000
b110011 '
1$
#1836000
0$
#1854000
b1101 !
b1101 %
b110100 '
1$
#1872000
0$
#1890000
b110101 '
1$
#1908000
0$
#1926000
b110110 '
1$
#1944000
0$
#1962000
b110111 '
1$
#1980000
0$
#1998000
b1110 !
b1110 %
b111000 '
1$
#2016000
0$
#2034000
b111001 '
1$
#2052000
0$
#2070000
b111010 '
1$
#2088000
0$
#2106000
b111011 '
1$
#2124000
0$
#2142000
b1111 !
b1111 %
b111100 '
1$
#2160000
0$
#2178000
b111101 '
1$
#2196000
0$
#2214000
b111110 '
1$
#2232000
0$
#2250000
b111111 '
1$
#2268000
0$
#2286000
b10000 !
b10000 %
b1000000 '
1$
#2304000
0$
#2322000
b1000001 '
1$
#2340000
0$
#2358000
b1000010 '
1$
#2376000
0$
#2394000
b1000011 '
1$
#2412000
0$
#2430000
b10001 !
b10001 %
b1000100 '
1$
#2448000
0$
#2466000
b1000101 '
1$
#2484000
0$
#2502000
b1000110 '
1$
#2520000
0$
#2538000
b1000111 '
1$
#2556000
0$
#2574000
b10010 !
b10010 %
b1001000 '
1$
#2592000
0$
#2610000
b1001001 '
1$
#2628000
0$
#2646000
b1001010 '
1$
#2664000
0$
#2682000
b1001011 '
1$
#2700000
0$
#2718000
b10011 !
b10011 %
b1001100 '
1$
#2736000
0$
#2754000
b1001101 '
1$
#2772000
0$
#2790000
b1001110 '
1$
#2808000
0$
#2826000
b1001111 '
1$
#2844000
0$
#2862000
b10100 !
b10100 %
b1010000 '
1$
#2880000
0$
#2898000
b1010001 '
1$
#2916000
0$
#2934000
b1010010 '
1$
#2952000
0$
#2970000
b1010011 '
1$
#2988000
0$
#3006000
b10101 !
b10101 %
b1010100 '
1$
#3024000
0$
#3042000
b1010101 '
1$
#3060000
0$
#3078000
b1010110 '
1$
#3096000
0$
#3114000
b1010111 '
1$
#3132000
0$
#3150000
b10110 !
b10110 %
b1011000 '
1$
#3168000
0$
#3186000
b1011001 '
1$
#3204000
0$
#3222000
b1011010 '
1$
#3240000
0$
#3258000
b1011011 '
1$
#3276000
0$
#3294000
b10111 !
b10111 %
b1011100 '
1$
#3312000
0$
#3330000
b1011101 '
1$
#3348000
0$
#3366000
b1011110 '
1$
#3384000
0$
#3402000
b1011111 '
1$
#3420000
0$
#3438000
b11000 !
b11000 %
b1100000 '
1$
#3456000
0$
#3474000
b1100001 '
1$
#3492000
0$
#3510000
b1100010 '
1$
#3528000
0$
#3546000
b1100011 '
1$
#3564000
0$
#3582000
b11001 !
b11001 %
b1100100 '
1$
#3600000
0$
#3618000
b1100101 '
1$
#3636000
0$
#3654000
b1100110 '
1$
#3672000
0$
#3690000
b1100111 '
1$
#3708000
0$
#3726000
b11010 !
b11010 %
b1101000 '
1$
#3744000
0$
#3762000
b1101001 '
1$
#3780000
0$
#3798000
b1101010 '
1$
#3816000
0$
#3834000
b1101011 '
1$
#3852000
0$
#3870000
b11011 !
b11011 %
b1101100 '
1$
#3888000
0$
#3906000
b1101101 '
1$
#3924000
0$
#3942000
b1101110 '
1$
#3960000
0$
#3978000
b1101111 '
1$
#3996000
0$
#4014000
b11100 !
b11100 %
b1110000 '
1$
#4032000
0$
#4050000
b1110001 '
1$
#4068000
0$
#4086000
b1110010 '
1$
#4104000
0$
#4122000
b1110011 '
1$
#4140000
0$
#4158000
b11101 !
b11101 %
b1110100 '
1$
#4176000
0$
#4194000
b1110101 '
1$
#4212000
0$
#4230000
b1110110 '
1$
#4248000
0$
#4266000
b1110111 '
1$
#4284000
0$
#4302000
b11110 !
b11110 %
b1111000 '
1$
#4320000
0$
#4338000
b1111001 '
1$
#4356000
0$
#4374000
b1111010 '
1$
#4392000
0$
#4410000
b1111011 '
1$
#4428000
0$
#4446000
b11111 !
b11111 %
b1111100 '
1$
#4464000
0$
#4482000
b1111101 '
1$
#4500000
0$
#4518000
b1111110 '
1$
#4536000
0$
#4554000
b1111111 '
1$
#4572000
0$
#4590000
b100000 !
b100000 %
b10000000 '
1$
#4608000
0$
#4626000
b10000001 '
1$
#4644000
0$
#4662000
b10000010 '
1$
#4680000
0$
#4698000
b10000011 '
1$
#4716000
0$
#4734000
b100001 !
b100001 %
b10000100 '
1$
#4752000
0$
#4770000
b10000101 '
1$
#4788000
0$
#4806000
b10000110 '
1$
#4824000
0$
#4842000
b10000111 '
1$
#4860000
0$
#4878000
b100010 !
b100010 %
b10001000 '
1$
#4896000
0$
#4914000
b10001001 '
1$
#4932000
0$
#4950000
b10001010 '
1$
#4968000
0$
#4986000
b10001011 '
1$
#5004000
0$
#5022000
b100011 !
b100011 %
b10001100 '
1$
#5040000
0$
#5058000
b10001101 '
1$
#5076000
0$
#5094000
b10001110 '
1$
#5112000
0$
#5130000
b10001111 '
1$
#5148000
0$
#5166000
b100100 !
b100100 %
b10010000 '
1$
#5184000
0$
#5202000
b10010001 '
1$
#5220000
0$
#5238000
b10010010 '
1$
#5256000
0$
#5274000
b10010011 '
1$
#5292000
0$
#5310000
b100101 !
b100101 %
b10010100 '
1$
#5328000
0$
#5346000
b10010101 '
1$
#5364000
0$
#5382000
b10010110 '
1$
#5400000
0$
#5418000
b10010111 '
1$
#5436000
0$
#5454000
b100110 !
b100110 %
b10011000 '
1$
#5472000
0$
#5490000
b10011001 '
1$
#5508000
0$
#5526000
b10011010 '
1$
#5544000
0$
#5562000
b10011011 '
1$
#5580000
0$
#5598000
b100111 !
b100111 %
b10011100 '
1$
#5616000
0$
#5634000
b10011101 '
1$
#5652000
0$
#5670000
b10011110 '
1$
#5688000
0$
#5706000
b10011111 '
1$
#5724000
0$
#5742000
b101000 !
b101000 %
b10100000 '
1$
#5760000
0$
#5778000
b10100001 '
1$
#5796000
0$
#5814000
b10100010 '
1$
#5832000
0$
#5850000
b10100011 '
1$
#5868000
0$
#5886000
b101001 !
b101001 %
b10100100 '
1$
#5904000
0$
#5922000
b10100101 '
1$
#5940000
0$
#5958000
b10100110 '
1$
#5976000
0$
#5994000
b10100111 '
1$
#6012000
0$
#6030000
b101010 !
b101010 %
b10101000 '
1$
#6048000
0$
#6066000
b10101001 '
1$
#6084000
0$
#6102000
b10101010 '
1$
#6120000
0$
#6138000
b10101011 '
1$
#6156000
0$
#6174000
b101011 !
b101011 %
b10101100 '
1$
#6192000
0$
#6210000
b10101101 '
1$
#6228000
0$
#6246000
b10101110 '
1$
#6264000
0$
#6282000
b10101111 '
1$
#6300000
0$
#6318000
b101100 !
b101100 %
b10110000 '
1$
#6336000
0$
#6354000
b10110001 '
1$
#6372000
0$
#6390000
b10110010 '
1$
#6408000
0$
#6426000
b10110011 '
1$
#6444000
0$
#6462000
b101101 !
b101101 %
b10110100 '
1$
#6480000
0$
#6498000
b10110101 '
1$
#6516000
0$
#6534000
b10110110 '
1$
#6552000
0$
#6570000
b10110111 '
1$
#6588000
0$
#6606000
b101110 !
b101110 %
b10111000 '
1$
#6624000
0$
#6642000
b10111001 '
1$
#6660000
0$
#6678000
b10111010 '
1$
#6696000
0$
#6714000
b10111011 '
1$
#6732000
0$
#6750000
b101111 !
b101111 %
b10111100 '
1$
#6768000
0$
#6786000
b10111101 '
1$
#6804000
0$
#6822000
b10111110 '
1$
#6840000
0$
#6858000
b10111111 '
1$
#6876000
0$
#6894000
b110000 !
b110000 %
b11000000 '
1$
#6912000
0$
#6930000
b11000001 '
1$
#6948000
0$
#6966000
b11000010 '
1$
#6984000
0$
#7002000
b11000011 '
1$
#7020000
0$
#7038000
b110001 !
b110001 %
b11000100 '
1$
#7056000
0$
#7074000
b11000101 '
1$
#7092000
0$
#7110000
b11000110 '
1$
#7128000
0$
#7146000
b11000111 '
1$
#7164000
0$
#7182000
b110010 !
b110010 %
b11001000 '
1$
#7200000
0$
#7218000
b11001001 '
1$
#7236000
0$
#7254000
b11001010 '
1$
#7272000
0$
#7290000
b11001011 '
1$
#7308000
0$
#7326000
b110011 !
b110011 %
b11001100 '
1$
#7344000
0$
#7362000
b11001101 '
1$
#7380000
0$
#7398000
b11001110 '
1$
#7416000
0$
#7434000
b11001111 '
1$
#7452000
0$
#7470000
b110100 !
b110100 %
b11010000 '
1$
#7488000
0$
#7506000
b11010001 '
1$
#7524000
0$
#7542000
b11010010 '
1$
#7560000
0$
#7578000
b11010011 '
1$
#7596000
0$
#7614000
b110101 !
b110101 %
b11010100 '
1$
#7632000
0$
#7650000
b11010101 '
1$
#7668000
0$
#7686000
b11010110 '
1$
#7704000
0$
#7722000
b11010111 '
1$
#7740000
0$
#7758000
b110110 !
b110110 %
b11011000 '
1$
#7776000
0$
#7794000
b11011001 '
1$
#7812000
0$
#7830000
b11011010 '
1$
#7848000
0$
#7866000
b11011011 '
1$
#7884000
0$
#7902000
b110111 !
b110111 %
b11011100 '
1$
#7920000
0$
#7938000
b11011101 '
1$
#7956000
0$
#7974000
b11011110 '
1$
#7992000
0$
#8010000
b11011111 '
1$
#8028000
0$
#8046000
b111000 !
b111000 %
b11100000 '
1$
#8064000
0$
#8082000
b11100001 '
1$
#8100000
0$
#8118000
b11100010 '
1$
#8136000
0$
#8154000
b11100011 '
1$
#8172000
0$
#8190000
b111001 !
b111001 %
b11100100 '
1$
#8208000
0$
#8226000
b11100101 '
1$
#8244000
0$
#8262000
b11100110 '
1$
#8280000
0$
#8298000
b11100111 '
1$
#8316000
0$
#8334000
b111010 !
b111010 %
b11101000 '
1$
#8352000
0$
#8370000
b11101001 '
1$
#8388000
0$
#8406000
b11101010 '
1$
#8424000
0$
#8442000
b11101011 '
1$
#8460000
0$
#8478000
b111011 !
b111011 %
b11101100 '
1$
#8496000
0$
#8514000
b11101101 '
1$
#8532000
0$
#8550000
b11101110 '
1$
#8568000
0$
#8586000
b11101111 '
1$
#8604000
0$
#8622000
b111100 !
b111100 %
b11110000 '
1$
#8640000
0$
#8658000
b11110001 '
1$
#8676000
0$
#8694000
b11110010 '
1$
#8712000
0$
#8730000
b11110011 '
1$
#8748000
0$
#8766000
b111101 !
b111101 %
b11110100 '
1$
#8784000
0$
#8802000
b11110101 '
1$
#8820000
0$
#8838000
b11110110 '
1$
#8856000
0$
#8874000
b11110111 '
1$
#8892000
0$
#8910000
b111110 !
b111110 %
b11111000 '
1$
#8928000
0$
#8946000
b11111001 '
1$
#8964000
0$
#8982000
b11111010 '
1$
#9000000
0$
#9018000
b11111011 '
1$
#9036000
0$
#9054000
b111111 !
b111111 %
b11111100 '
1$
#9072000
0$
#9090000
b11111101 '
1$
#9108000
0$
#9126000
b11111110 '
1$
#9144000
0$
#9162000
b11111111 '
1$
#9180000
0$
#9198000
b0 !
b0 %
b0 '
1$
#9216000
0$
#9234000
b1 '
1$
#9252000
0$
#9270000
b10 '
1$
#9288000
0$
#9306000
b11 '
1$
#9324000
0$
#9342000
b1 !
b1 %
b100 '
1$
#9360000
0$
#9378000
b101 '
1$
#9396000
0$
#9414000
b110 '
1$
#9432000
0$
#9450000
b111 '
1$
#9468000
0$
#9486000
b10 !
b10 %
b1000 '
1$
#9504000
0$
#9522000
b1001 '
1$
#9540000
0$
#9558000
b1010 '
1$
#9576000
0$
#9594000
b1011 '
1$
#9612000
0$
#9630000
b11 !
b11 %
b1100 '
1$
#9648000
0$
#9666000
b1101 '
1$
#9684000
0$
#9702000
b1110 '
1$
#9720000
0$
#9738000
b1111 '
1$
#9756000
0$
#9774000
b100 !
b100 %
b10000 '
1$
#9792000
0$
#9810000
b10001 '
1$
#9828000
0$
#9846000
b10010 '
1$
#9864000
0$
#9882000
b10011 '
1$
#9900000
0$
#9918000
b101 !
b101 %
b10100 '
1$
#9936000
0$
#9954000
b10101 '
1$
#9972000
0$
#9990000
b10110 '
1$
