FPGA_Test/top.v
// top.v - simple LED counter for FPGA
// Assumptions:
// - The board provides a clock input named `clk` (map your actual clock pin in the .cst file)
// - The LED pins are exposed as an 8-bit bus named `led` (map these signal names to board pins in io_tangnano9k.cst)
// If your .cst uses different signal names (for example LED0..LED7), either rename the
// outputs here or change the pin names in the .cst to match `led[0]`..`led[7]`.

module top (
    input  clk,            // external clock (map this pin in .cst)
    output [5:0] led       // 6 LEDs (led[0] is LSB, led[5] is MSB)
);

    // 6-bit free-running counter. It counts 0..63 and directly drives the 6 LEDs.
    // Note: counting on every FPGA clock edge may be very fast; this matches your
    // request to make the counter 6 bits only. If you want visible slow blinking,
    // either feed a slower clock or add a wider prescaler.

    // Use a wider counter for slower blinking (24 bits => bits 23 downto 0)
    localparam COUNTER_WIDTH = 8;
    reg [COUNTER_WIDTH-1:0] counter = 0;

    always @(posedge clk) begin
        counter <= counter + 1'b1;
    end

    // Directly present the counter on the LED pins
    // Use the top 6 bits of the counter. previous code referenced bit 24 which is out of range
    // for a 24-bit counter (0..23). Use COUNTER_WIDTH-1 downto COUNTER_WIDTH-6 instead.
    assign led[5:0] = counter[COUNTER_WIDTH-1:COUNTER_WIDTH-6]; // upper 6 bits for visible blinking

endmodule

FPGA_Test/test_tb.v
`timescale 1ns/1ps

// test.tsb - simple testbench for top.v
// Simulates the `top` module for 3 seconds and writes a VCD file (test.vcd).

module tb_top;
    // Testbench clock and DUT wires
    reg clk;
    wire [5:0] led;

    // Instantiate the design under test
    top uut (
        .clk(clk),
        .led(led)
    );

    // Clock generation: use 27 MHz clock
    // Period = 1e9 ns / 27e6 = ~37.037037 ns
    real PERIOD_NS = 1000000000.0 / 27000000.0; // ns
    real HALF = PERIOD_NS / 2.0;

    initial begin
        clk = 0;
        forever #(HALF) clk = ~clk;
    end

    // Run simulation for 3 seconds
    initial begin
        $display("Starting simulation at %0t ns", $time);
        $dumpfile("test.vcd");
        $dumpvars(0, tb_top);
        $monitor("%0t ns : clk=%b led=%b", $time, clk, led);

        // 10 us = 10_000 ns
        #10000;

        $display("Ending simulation at %0t ns", $time);
        $finish;
    end

endmodule

FPGA_Test/test.vcd
$date
	Thu Nov 27 16:06:17 2025
$end
$version
	Icarus Verilog
$end
$timescale
	1ps
$end
$scope module tb_top $end
$var wire 6 ! led [5:0] $end
$var reg 1 " clk $end
$var real 1 # HALF $end
$var real 1 $ PERIOD_NS $end
$scope module uut $end
$var wire 1 " clk $end
$var wire 6 % led [5:0] $end
$var parameter 32 & COUNTER_WIDTH $end
$var reg 8 ' counter [7:0] $end
$upscope $end
$upscope $end
$enddefinitions $end
$comment Show the parameter values. $end
$dumpall
b1000 &
$end
#0
$dumpvars
b0 '
b0 %
r37.03703703703704 $
r18.51851851851852 #
0"
b0 !
$end
#18519
b1 '
1"
#37038
0"
#55557
b10 '
1"
#74076
0"
#92595
b11 '
1"
#111114
0"
#129633
b1 !
b1 %
b100 '
1"
#148152
0"
#166671
b101 '
1"
#185190
0"
#203709
b110 '
1"
#222228
0"
#240747
b111 '
1"
#259266
0"
#277785
b10 !
b10 %
b1000 '
1"
#296304
0"
#314823
b1001 '
1"
#333342
0"
#351861
b1010 '
1"
#370380
0"
#388899
b1011 '
1"
#407418
0"
#425937
b11 !
b11 %
b1100 '
1"
#444456
0"
#462975
b1101 '
1"
#481494
0"
#500013
b1110 '
1"
#518532
0"
#537051
b1111 '
1"
#555570
0"
#574089
b100 !
b100 %
b10000 '
1"
#592608
0"
#611127
b10001 '
1"
#629646
0"
#648165
b10010 '
1"
#666684
0"
#685203
b10011 '
1"
#703722
0"
#722241
b101 !
b101 %
b10100 '
1"
#740760
0"
#759279
b10101 '
1"
#777798
0"
#796317
b10110 '
1"
#814836
0"
#833355
b10111 '
1"
#851874
0"
#870393
b110 !
b110 %
b11000 '
1"
#888912
0"
#907431
b11001 '
1"
#925950
0"
#944469
b11010 '
1"
#962988
0"
#981507
b11011 '
1"
#1000026
0"
#1018545
b111 !
b111 %
b11100 '
1"
#1037064
0"
#1055583
b11101 '
1"
#1074102
0"
#1092621
b11110 '
1"
#1111140
0"
#1129659
b11111 '
1"
#1148178
0"
#1166697
b1000 !
b1000 %
b100000 '
1"
#1185216
0"
#1203735
b100001 '
1"
#1222254
0"
#1240773
b100010 '
1"
#1259292
0"
#1277811
b100011 '
1"
#1296330
0"
#1314849
b1001 !
b1001 %
b100100 '
1"
#1333368
0"
#1351887
b100101 '
1"
#1370406
0"
#1388925
b100110 '
1"
#1407444
0"
#1425963
b100111 '
1"
#1444482
0"
#1463001
b1010 !
b1010 %
b101000 '
1"
#1481520
0"
#1500039
b101001 '
1"
#1518558
0"
#1537077
b101010 '
1"
#1555596
0"
#1574115
b101011 '
1"
#1592634
0"
#1611153
b1011 !
b1011 %
b101100 '
1"
#1629672
0"
#1648191
b101101 '
1"
#1666710
0"
#1685229
b101110 '
1"
#1703748
0"
#1722267
b101111 '
1"
#1740786
0"
#1759305
b1100 !
b1100 %
b110000 '
1"
#1777824
0"
#1796343
b110001 '
1"
#1814862
0"
#1833381
b110010 '
1"
#1851900
0"
#1870419
b110011 '
1"
#1888938
0"
#1907457
b1101 !
b1101 %
b110100 '
1"
#1925976
0"
#1944495
b110101 '
1"
#1963014
0"
#1981533
b110110 '
1"
#2000052
0"
#2018571
b110111 '
1"
#2037090
0"
#2055609
b1110 !
b1110 %
b111000 '
1"
#2074128
0"
#2092647
b111001 '
1"
#2111166
0"
#2129685
b111010 '
1"
#2148204
0"
#2166723
b111011 '
1"
#2185242
0"
#2203761
b1111 !
b1111 %
b111100 '
1"
#2222280
0"
#2240799
b111101 '
1"
#2259318
0"
#2277837
b111110 '
1"
#2296356
0"
#2314875
b111111 '
1"
#2333394
0"
#2351913
b10000 !
b10000 %
b1000000 '
1"
#2370432
0"
#2388951
b1000001 '
1"
#2407470
0"
#2425989
b1000010 '
1"
#2444508
0"
#2463027
b1000011 '
1"
#2481546
0"
#2500065
b10001 !
b10001 %
b1000100 '
1"
#2518584
0"
#2537103
b1000101 '
1"
#2555622
0"
#2574141
b1000110 '
1"
#2592660
0"
#2611179
b1000111 '
1"
#2629698
0"
#2648217
b10010 !
b10010 %
b1001000 '
1"
#2666736
0"
#2685255
b1001001 '
1"
#2703774
0"
#2722293
b1001010 '
1"
#2740812
0"
#2759331
b1001011 '
1"
#2777850
0"
#2796369
b10011 !
b10011 %
b1001100 '
1"
#2814888
0"
#2833407
b1001101 '
1"
#2851926
0"
#2870445
b1001110 '
1"
#2888964
0"
#2907483
b1001111 '
1"
#2926002
0"
#2944521
b10100 !
b10100 %
b1010000 '
1"
#2963040
0"
#2981559
b1010001 '
1"
#3000078
0"
#3018597
b1010010 '
1"
#3037116
0"
#3055635
b1010011 '
1"
#3074154
0"
#3092673
b10101 !
b10101 %
b1010100 '
1"
#3111192
0"
#3129711
b1010101 '
1"
#3148230
0"
#3166749
b1010110 '
1"
#3185268
0"
#3203787
b1010111 '
1"
#3222306
0"
#3240825
b10110 !
b10110 %
b1011000 '
1"
#3259344
0"
#3277863
b1011001 '
1"
#3296382
0"
#3314901
b1011010 '
1"
#3333420
0"
#3351939
b1011011 '
1"
#3370458
0"
#3388977
b10111 !
b10111 %
b1011100 '
1"
#3407496
0"
#3426015
b1011101 '
1"
#3444534
0"
#3463053
b1011110 '
1"
#3481572
0"
#3500091
b1011111 '
1"
#3518610
0"
#3537129
b11000 !
b11000 %
b1100000 '
1"
#3555648
0"
#3574167
b1100001 '
1"
#3592686
0"
#3611205
b1100010 '
1"
#3629724
0"
#3648243
b1100011 '
1"
#3666762
0"
#3685281
b11001 !
b11001 %
b1100100 '
1"
#3703800
0"
#3722319
b1100101 '
1"
#3740838
0"
#3759357
b1100110 '
1"
#3777876
0"
#3796395
b1100111 '
1"
#3814914
0"
#3833433
b11010 !
b11010 %
b1101000 '
1"
#3851952
0"
#3870471
b1101001 '
1"
#3888990
0"
#3907509
b1101010 '
1"
#3926028
0"
#3944547
b1101011 '
1"
#3963066
0"
#3981585
b11011 !
b11011 %
b1101100 '
1"
#4000104
0"
#4018623
b1101101 '
1"
#4037142
0"
#4055661
b1101110 '
1"
#4074180
0"
#4092699
b1101111 '
1"
#4111218
0"
#4129737
b11100 !
b11100 %
b1110000 '
1"
#4148256
0"
#4166775
b1110001 '
1"
#4185294
0"
#4203813
b1110010 '
1"
#4222332
0"
#4240851
b1110011 '
1"
#4259370
0"
#4277889
b11101 !
b11101 %
b1110100 '
1"
#4296408
0"
#4314927
b1110101 '
1"
#4333446
0"
#4351965
b1110110 '
1"
#4370484
0"
#4389003
b1110111 '
1"
#4407522
0"
#4426041
b11110 !
b11110 %
b1111000 '
1"
#4444560
0"
#4463079
b1111001 '
1"
#4481598
0"
#4500117
b1111010 '
1"
#4518636
0"
#4537155
b1111011 '
1"
#4555674
0"
#4574193
b11111 !
b11111 %
b1111100 '
1"
#4592712
0"
#4611231
b1111101 '
1"
#4629750
0"
#4648269
b1111110 '
1"
#4666788
0"
#4685307
b1111111 '
1"
#4703826
0"
#4722345
b100000 !
b100000 %
b10000000 '
1"
#4740864
0"
#4759383
b10000001 '
1"
#4777902
0"
#4796421
b10000010 '
1"
#4814940
0"
#4833459
b10000011 '
1"
#4851978
0"
#4870497
b100001 !
b100001 %
b10000100 '
1"
#4889016
0"
#4907535
b10000101 '
1"
#4926054
0"
#4944573
b10000110 '
1"
#4963092
0"
#4981611
b10000111 '
1"
#5000130
0"
#5018649
b100010 !
b100010 %
b10001000 '
1"
#5037168
0"
#5055687
b10001001 '
1"
#5074206
0"
#5092725
b10001010 '
1"
#5111244
0"
#5129763
b10001011 '
1"
#5148282
0"
#5166801
b100011 !
b100011 %
b10001100 '
1"
#5185320
0"
#5203839
b10001101 '
1"
#5222358
0"
#5240877
b10001110 '
1"
#5259396
0"
#5277915
b10001111 '
1"
#5296434
0"
#5314953
b100100 !
b100100 %
b10010000 '
1"
#5333472
0"
#5351991
b10010001 '
1"
#5370510
0"
#5389029
b10010010 '
1"
#5407548
0"
#5426067
b10010011 '
1"
#5444586
0"
#5463105
b100101 !
b100101 %
b10010100 '
1"
#5481624
0"
#5500143
b10010101 '
1"
#5518662
0"
#5537181
b10010110 '
1"
#5555700
0"
#5574219
b10010111 '
1"
#5592738
0"
#5611257
b100110 !
b100110 %
b10011000 '
1"
#5629776
0"
#5648295
b10011001 '
1"
#5666814
0"
#5685333
b10011010 '
1"
#5703852
0"
#5722371
b10011011 '
1"
#5740890
0"
#5759409
b100111 !
b100111 %
b10011100 '
1"
#5777928
0"
#5796447
b10011101 '
1"
#5814966
0"
#5833485
b10011110 '
1"
#5852004
0"
#5870523
b10011111 '
1"
#5889042
0"
#5907561
b101000 !
b101000 %
b10100000 '
1"
#5926080
0"
#5944599
b10100001 '
1"
#5963118
0"
#5981637
b10100010 '
1"
#6000156
0"
#6018675
b10100011 '
1"
#6037194
0"
#6055713
b101001 !
b101001 %
b10100100 '
1"
#6074232
0"
#6092751
b10100101 '
1"
#6111270
0"
#6129789
b10100110 '
1"
#6148308
0"
#6166827
b10100111 '
1"
#6185346
0"
#6203865
b101010 !
b101010 %
b10101000 '
1"
#6222384
0"
#6240903
b10101001 '
1"
#6259422
0"
#6277941
b10101010 '
1"
#6296460
0"
#6314979
b10101011 '
1"
#6333498
0"
#6352017
b101011 !
b101011 %
b10101100 '
1"
#6370536
0"
#6389055
b10101101 '
1"
#6407574
0"
#6426093
b10101110 '
1"
#6444612
0"
#6463131
b10101111 '
1"
#6481650
0"
#6500169
b101100 !
b101100 %
b10110000 '
1"
#6518688
0"
#6537207
b10110001 '
1"
#6555726
0"
#6574245
b10110010 '
1"
#6592764
0"
#6611283
b10110011 '
1"
#6629802
0"
#6648321
b101101 !
b101101 %
b10110100 '
1"
#6666840
0"
#6685359
b10110101 '
1"
#6703878
0"
#6722397
b10110110 '
1"
#6740916
0"
#6759435
b10110111 '
1"
#6777954
0"
#6796473
b101110 !
b101110 %
b10111000 '
1"
#6814992
0"
#6833511
b10111001 '
1"
#6852030
0"
#6870549
b10111010 '
1"
#6889068
0"
#6907587
b10111011 '
1"
#6926106
0"
#6944625
b101111 !
b101111 %
b10111100 '
1"
#6963144
0"
#6981663
b10111101 '
1"
#7000182
0"
#7018701
b10111110 '
1"
#7037220
0"
#7055739
b10111111 '
1"
#7074258
0"
#7092777
b110000 !
b110000 %
b11000000 '
1"
#7111296
0"
#7129815
b11000001 '
1"
#7148334
0"
#7166853
b11000010 '
1"
#7185372
0"
#7203891
b11000011 '
1"
#7222410
0"
#7240929
b110001 !
b110001 %
b11000100 '
1"
#7259448
0"
#7277967
b11000101 '
1"
#7296486
0"
#7315005
b11000110 '
1"
#7333524
0"
#7352043
b11000111 '
1"
#7370562
0"
#7389081
b110010 !
b110010 %
b11001000 '
1"
#7407600
0"
#7426119
b11001001 '
1"
#7444638
0"
#7463157
b11001010 '
1"
#7481676
0"
#7500195
b11001011 '
1"
#7518714
0"
#7537233
b110011 !
b110011 %
b11001100 '
1"
#7555752
0"
#7574271
b11001101 '
1"
#7592790
0"
#7611309
b11001110 '
1"
#7629828
0"
#7648347
b11001111 '
1"
#7666866
0"
#7685385
b110100 !
b110100 %
b11010000 '
1"
#7703904
0"
#7722423
b11010001 '
1"
#7740942
0"
#7759461
b11010010 '
1"
#7777980
0"
#7796499
b11010011 '
1"
#7815018
0"
#7833537
b110101 !
b110101 %
b11010100 '
1"
#7852056
0"
#7870575
b11010101 '
1"
#7889094
0"
#7907613
b11010110 '
1"
#7926132
0"
#7944651
b11010111 '
1"
#7963170
0"
#7981689
b110110 !
b110110 %
b11011000 '
1"
#8000208
0"
#8018727
b11011001 '
1"
#8037246
0"
#8055765
b11011010 '
1"
#8074284
0"
#8092803
b11011011 '
1"
#8111322
0"
#8129841
b110111 !
b110111 %
b11011100 '
1"
#8148360
0"
#8166879
b11011101 '
1"
#8185398
0"
#8203917
b11011110 '
1"
#8222436
0"
#8240955
b11011111 '
1"
#8259474
0"
#8277993
b111000 !
b111000 %
b11100000 '
1"
#8296512
0"
#8315031
b11100001 '
1"
#8333550
0"
#8352069
b11100010 '
1"
#8370588
0"
#8389107
b11100011 '
1"
#8407626
0"
#8426145
b111001 !
b111001 %
b11100100 '
1"
#8444664
0"
#8463183
b11100101 '
1"
#8481702
0"
#8500221
b11100110 '
1"
#8518740
0"
#8537259
b11100111 '
1"
#8555778
0"
#8574297
b111010 !
b111010 %
b11101000 '
1"
#8592816
0"
#8611335
b11101001 '
1"
#8629854
0"
#8648373
b11101010 '
1"
#8666892
0"
#8685411
b11101011 '
1"
#8703930
0"
#8722449
b111011 !
b111011 %
b11101100 '
1"
#8740968
0"
#8759487
b11101101 '
1"
#8778006
0"
#8796525
b11101110 '
1"
#8815044
0"
#8833563
b11101111 '
1"
#8852082
0"
#8870601
b111100 !
b111100 %
b11110000 '
1"
#8889120
0"
#8907639
b11110001 '
1"
#8926158
0"
#8944677
b11110010 '
1"
#8963196
0"
#8981715
b11110011 '
1"
#9000234
0"
#9018753
b111101 !
b111101 %
b11110100 '
1"
#9037272
0"
#9055791
b11110101 '
1"
#9074310
0"
#9092829
b11110110 '
1"
#9111348
0"
#9129867
b11110111 '
1"
#9148386
0"
#9166905
b111110 !
b111110 %
b11111000 '
1"
#9185424
0"
#9203943
b11111001 '
1"
#9222462
0"
#9240981
b11111010 '
1"
#9259500
0"
#9278019
b11111011 '
1"
#9296538
0"
#9315057
b111111 !
b111111 %
b11111100 '
1"
#9333576
0"
#9352095
b11111101 '
1"
#9370614
0"
#9389133
b11111110 '
1"
#9407652
0"
#9426171
b11111111 '
1"
#9444690
0"
#9463209
b0 !
b0 %
b0 '
1"
#9481728
0"
#9500247
b1 '
1"
#9518766
0"
#9537285
b10 '
1"
#9555804
0"
#9574323
b11 '
1"
#9592842
0"
#9611361
b1 !
b1 %
b100 '
1"
#9629880
0"
#9648399
b101 '
1"
#9666918
0"
#9685437
b110 '
1"
#9703956
0"
#9722475
b111 '
1"
#9740994
0"
#9759513
b10 !
b10 %
b1000 '
1"
#9778032
0"
#9796551
b1001 '
1"
#9815070
0"
#9833589
b1010 '
1"
#9852108
0"
#9870627
b1011 '
1"
#9889146
0"
#9907665
b11 !
b11 %
b1100 '
1"
#9926184
0"
#9944703
b1101 '
1"
#9963222
0"
#9981741
b1110 '
1"
